Workbook

Sheet Original Data
A1: transaction_id | B1: product_id | C1: sale_date | D1: product_name | E1: brand | F1: store_id | G1: region | H1: quantity | I1: discount | J1: total | K1: payment_method | L1: sales_rep | M1: is_active
A2: 1 | B2: P001 | C2: 45031 | D2: Classic Crew-Neck Tee | E2: GAP | F2: S002 | G2: West | H2: 3 | I2: 0 | J2: 59.97 | K2: DEBIT CARD | M2: 0
A3: 2 | B3: P008 | C3: 45641 | D3: Denim Jacket | E3: GAP | F3: S007 | G3: Northeast | H3: 4 | I3: 0.1 | J3: 323.82 | K3: DEBIT CARD | L3: Maria S. | M3: TRUE
A4: 3 | B4: P015 | C4: 45492 | D4: NULL | E4: NULL | F4: S001 | G4: Northeast | H4: 5 | I4: 0 | J4: 224.75 | K4: CREDIT CARD | L4: Priya M. | M4: NULL
A5: 4 | B5: P008 | C5: 45577 | D5: NULL | E5: NULL | F5: S002 | G5: West | H5: 1 | I5: 0.2 | J5: 71.96 | K5: GIFT CARD | L5: Amy K. | M5: NULL
A6: 5 | B6: P006 | C6: 45631 | D6: Floral Midi Dress | E6: Banana Republic | F6: S004 | G6: South | H6: 4 | I6: 0 | J6: 319.8 | K6: APPLE PAY | M6: FALSE
A7: 6 | B7: P007 | C7: 45198 | D7: Running Leggings | E7: Athleta | F7: S006 | G7: West | H7: 4 | I7: 0.2 | J7: 207.84 | K7: DEBIT CARD | L7: Tom B. | M7: 1
A8: 7 | B8: P003 | C8: 45090 | D8: puffer jacket | E8: GAP | F8: S008 | H8: 1 | I8: 0 | J8: 129 | K8: APPLE PAY | L8: Lin W. | M8: TRUE
A9: 8 | B9: P004 | C9: 45227 | D9: Canvas Sneakers | E9: Old Navy | F9: S001 | G9: Northeast | H9: 5 | I9: 0.1 | J9: 224.78 | K9: CREDIT CARD | L9: David N. | M9: 0
A10: 9 | B10: P010 | C10: 45092 | D10: High-Rise Jeans | E10: GAP | F10: S002 | G10: West | H10: 5 | I10: 0.05 | J10: 332.26 | K10: CASH | L10: Lin W. | M10: 0
A11: 10 | B11: P008 | C11: 45424 | D11: Denim Jacket | E11: GAP | F11: S005 | G11: Southeast | H11: 1 | I11: 0.05 | J11: 85.45 | K11: CREDIT CARD | L11: James T. | M11: TRUE
A12: 11 | B12: P018 | C12: 45592 | D12: Rain Jacket | E12: Old Navy | F12: S004 | G12: South | H12: 2 | I12: 0.1 | J12: 153 | K12: APPLE PAY | L12: Priya M. | M12: 1
A13: 12 | B13: P002 | C13: 44999 | D13: Slim Chino Pants | E13: GAP | F13: S002 | G13: West | H13: 2 | I13: 0 | J13: 119.9 | K13: CASH | L13: Maria S. | M13: 1
A14: 13 | B14: P007 | C14: 45360 | D14: Running Leggings | E14: Athleta | F14: S007 | G14: Northeast | H14: 1 | I14: 0 | J14: 64.95 | K14: CASH | L14: Priya M. | M14: 1
A15: 14 | B15: P007 | C15: 45114 | D15: Running Leggings | E15: Athleta | F15: S004 | G15: South | H15: 2 | I15: 0.25 | J15: 97.43 | K15: GIFT CARD | L15: Lin W. | M15: 1
A16: 15 | B16: P003 | C16: 45419 | D16: puffer jacket | E16: GAP | F16: S001 | G16: Northeast | H16: 2 | I16: NA | J16: 258 | K16: GIFT CARD | L16: Priya M. | M16: TRUE
A17: 16 | B17: P005 | C17: 45520 | D17: Leather Belt | E17: Banana Republic | F17: S008 | H17: 2 | I17: 0.1 | J17: 62.98 | K17: CREDIT CARD | L17: Carlos R. | M17: 0
A18: 17 | B18: P006 | C18: 45049 | D18: Floral Midi Dress | E18: Banana Republic | F18: S002 | G18: West | H18: 1 | I18: 0 | J18: 79.95 | K18: GIFT CARD | L18: Carlos R. | M18: FALSE
A19: 18 | B19: P008 | C19: 45587 | D19: Denim Jacket | E19: GAP | F19: S006 | G19: West | H19: 3 | I19: 0 | J19: 269.85 | K19: APPLE PAY | L19: Lin W. | M19: TRUE
A20: 19 | B20: P008 | C20: 45483 | D20: Denim Jacket | E20: GAP | F20: S002 | G20: West | H20: 3 | I20: 0.1 | J20: 242.87 | K20: GIFT CARD | L20: Lin W. | M20: TRUE
A21: 20 | B21: P009 | C21: 45215 | D21: Wool Sweater | E21: Banana Republic | F21: S003 | G21: Midwest | H21: 1 | I21: 0 | J21: 74.95 | K21: CASH | L21: Lin W. | M21: 0
A22: 21 | B22: P009 | C22: 45579 | D22: Wool Sweater | E22: Banana Republic | F22: S007 | G22: Northeast | H22: 1 | I22: 0 | J22: 74.95 | K22: DEBIT CARD | L22: David N. | M22: 0
A23: 22 | B23: P012 | C23: 44969 | D23: Ankle Boots | E23: Banana Republic | F23: S001 | G23: Northeast | H23: 5 | I23: n/a | J23: 595 | K23: DEBIT CARD | L23: Priya M. | M23: FALSE
A24: 23 | B24: P020 | C24: 45349 | D24: Crossbody Bag | E24: Banana Republic | F24: S007 | G24: Northeast | H24: 2 | I24: 0.05 | J24: 113.9 | K24: DEBIT CARD | L24: Lin W. | M24: Yes
A25: 24 | B25: P013 | C25: 45398 | D25: Silk Scarf | E25: Intermix | F25: S002 | G25: West | H25: 1 | J25: 44.95 | K25: DEBIT CARD | M25: No
A26: 25 | B26: P017 | C26: 45194 | D26: Cargo Shorts | E26: Old Navy | F26: S006 | G26: West | H26: 4 | I26: 0.15 | J26: 135.83 | K26: CREDIT CARD | L26: Maria S. | M26: 1
A27: 26 | B27: P013 | C27: 45652 | D27: Silk Scarf | E27: Intermix | G27: NULL | H27: 5 | I27: 0.05 | J27: 213.51 | K27: CREDIT CARD | L27: Amy K. | M27: No
A28: 27 | B28: P020 | C28: 45243 | D28: Crossbody Bag | E28: Banana Republic | F28: S006 | G28: West | H28: 3 | I28: 0 | J28: 179.85 | K28: PAYPAL | L28: Amy K. | M28: Yes
A29: 28 | B29: P013 | C29: 45142 | D29: Silk Scarf | E29: Intermix | F29: S005 | G29: Southeast | H29: 5 | I29: 0 | J29: 224.75 | K29: CASH | L29: Amy K. | M29: No
A30: 29 | B30: P003 | C30: 45615 | D30: puffer jacket | E30: GAP | F30: S003 | G30: Midwest | H30: 3 | I30: 0.15 | J30: 328.95 | K30: DEBIT CARD | L30: James T. | M30: TRUE
A31: 30 | B31: P013 | C31: 45598 | D31: Silk Scarf | E31: Intermix | G31: NULL | H31: 4 | I31: 0.2 | J31: 143.84 | K31: DEBIT CARD | L31: Carlos R. | M31: No
A32: 31 | B32: P018 | C32: 45402 | D32: Rain Jacket | E32: Old Navy | F32: S001 | G32: Northeast | H32: 2 | I32: 0 | J32: 170 | K32: DEBIT CARD | L32: Tom B. | M32: 1
A33: 32 | B33: P006 | C33: 45579 | D33: Floral Midi Dress | E33: Banana Republic | F33: S008 | H33: 4 | I33: 0.25 | J33: 239.85 | K33: DEBIT CARD | L33: Amy K. | M33: FALSE
A34: 33 | B34: P005 | C34: 45083 | D34: Leather Belt | E34: Banana Republic | F34: S002 | G34: West | H34: 2 | I34: 0.05 | J34: 66.48 | K34: APPLE PAY | L34: Priya M. | M34: 0
A35: 34 | B35: P019 | C35: 45232 | D35: Slip-On Loafers | E35: GAP | F35: S001 | G35: Northeast | H35: 4 | I35: 0.25 | J35: 239.85 | K35: CASH | L35: Maria S. | M35: Yes
A36: 35 | B36: P016 | C36: 45622 | D36: Graphic Hoodie | E36: Old Navy | F36: S007 | G36: Northeast | H36: 1 | I36: 0.2 | J36: 39.96 | K36: APPLE PAY | L36: David N. | M36: 0
A37: 36 | B37: P014 | C37: 45193 | D37: Wrap Dress | E37: Intermix | F37: S002 | G37: West | H37: 2 | I37: 0.25 | J37: 134.93 | K37: CREDIT CARD | L37: Lin W. | M37: Yes
A38: 37 | B38: P001 | C38: 45592 | D38: NULL | E38: NULL | F38: S008 | H38: 5 | I38: 0 | J38: 99.95 | K38: DEBIT CARD | L38: David N. | M38: NULL
A39: 38 | B39: P019 | C39: 45098 | D39: Slip-On Loafers | E39: GAP | F39: S002 | G39: West | H39: 2 | I39: 0.25 | J39: 119.93 | K39: CASH | M39: Yes
A40: 39 | B40: P013 | C40: 45640 | D40: Silk Scarf | E40: Intermix | F40: S007 | G40: Northeast | H40: 2 | I40: 0 | J40: 89.9 | K40: CREDIT CARD | L40: Carlos R. | M40: No
A41: 40 | B41: P001 | C41: 45297 | D41: Classic Crew-Neck Tee | E41: GAP | F41: S006 | G41: West | H41: 4 | I41: 0.25 | J41: 59.97 | K41: GIFT CARD | L41: James T. | M41: 0
A42: 41 | B42: P015 | C42: 45015 | D42: NULL | E42: NULL | F42: S008 | H42: 4 | I42: 0.1 | J42: 161.82 | K42: DEBIT CARD | L42: David N. | M42: NULL
A43: 42 | B43: P012 | C43: 45645 | D43: Ankle Boots | E43: Banana Republic | F43: S004 | G43: South | H43: 3 | I43: 0.15 | J43: 303.45 | K43: PAYPAL | L43: Amy K. | M43: FALSE
A44: 43 | B44: P015 | C44: 45341 | D44: Sports Bra | E44: Athleta | F44: S008 | H44: 1 | I44: 0 | J44: 44.95 | K44: DEBIT CARD | L44: Amy K. | M44: TRUE
A45: 44 | B45: P009 | C45: 45124 | D45: Wool Sweater | E45: Banana Republic | F45: S008 | H45: 3 | I45: 0.1 | J45: 202.37 | K45: CREDIT CARD | L45: Carlos R. | M45: 0
A46: 45 | B46: P004 | C46: 45110 | D46: Canvas Sneakers | E46: Old Navy | G46: NULL | H46: 2 | I46: 0.1 | J46: 89.91 | K46: CASH | L46: Carlos R. | M46: 0
A47: 46 | B47: P004 | C47: 45378 | D47: Canvas Sneakers | E47: Old Navy | F47: S008 | H47: 1 | I47: 0.1 | J47: 44.96 | K47: GIFT CARD | L47: Tom B. | M47: 0
A48: 47 | B48: P005 | C48: 45048 | D48: Leather Belt | E48: Banana Republic | F48: S001 | G48: Northeast | H48: 2 | I48: 0.1 | J48: 62.98 | K48: DEBIT CARD | L48: James T. | M48: 0
A49: 48 | B49: P010 | C49: 45567 | D49: High-Rise Jeans | E49: GAP | F49: S007 | G49: Northeast | H49: 5 | I49: 0 | J49: 349.75 | K49: DEBIT CARD | L49: James T. | M49: 0
A50: 49 | B50: P010 | C50: 45216 | D50: High-Rise Jeans | E50: GAP | F50: S008 | H50: 1 | I50: 0.05 | J50: 66.45 | K50: APPLE PAY | L50: Amy K. | M50: 0
A51: 50 | B51: P014 | C51: 45072 | D51: Wrap Dress | E51: Intermix | F51: S004 | G51: South | H51: 1 | I51: 0.05 | J51: 85.45 | K51: CASH | L51: Lin W. | M51: Yes
A52: 51 | B52: P009 | C52: 45539 | D52: Wool Sweater | E52: Banana Republic | F52: S007 | G52: Northeast | H52: 5 | J52: 374.75 | K52: CREDIT CARD | L52: Tom B. | M52: 0
A53: 52 | B53: P019 | C53: 45594 | D53: Slip-On Loafers | E53: GAP | F53: S005 | G53: Southeast | H53: 1 | I53: 0 | J53: 79.95 | K53: PAYPAL | L53: Tom B. | M53: Yes
A54: 53 | B54: P006 | C54: 45605 | D54: Floral Midi Dress | E54: Banana Republic | F54: S002 | G54: West | H54: 3 | I54: 0.2 | J54: 191.88 | K54: CASH | L54: Tom B. | M54: FALSE
A55: 54 | B55: P018 | C55: 45457 | D55: Rain Jacket | E55: Old Navy | F55: S001 | G55: Northeast | H55: 4 | I55: n/a | J55: 340 | K55: DEBIT CARD | L55: Maria S. | M55: 1
A56: 55 | B56: P001 | C56: 45491 | D56: Classic Crew-Neck Tee | E56: GAP | F56: S002 | G56: West | H56: 5 | I56: 0.05 | J56: 94.95 | K56: CASH | L56: Lin W. | M56: 0
A57: 56 | B57: P010 | C57: 45410 | D57: High-Rise Jeans | E57: GAP | F57: S008 | H57: 5 | I57: 0.1 | J57: 314.78 | K57: GIFT CARD | L57: Priya M. | M57: 0
A58: 57 | B58: P011 | C58: 45232 | D58: Trench Coat | E58: Banana Republic | F58: S007 | G58: Northeast | H58: 5 | I58: 0.1 | J58: 891 | K58: CASH | L58: Maria S. | M58: FALSE
A59: 58 | B59: P007 | C59: 44971 | D59: Running Leggings | E59: Athleta | F59: S006 | G59: West | H59: 2 | I59: 0.2 | J59: 103.92 | K59: GIFT CARD | L59: Carlos R. | M59: 1
A60: 59 | B60: P005 | C60: 45029 | D60: Leather Belt | E60: Banana Republic | F60: S001 | G60: Northeast | H60: 5 | I60: 0.15 | J60: 148.71 | K60: GIFT CARD | L60: James T. | M60: 0
A61: 60 | B61: P011 | C61: 45617 | D61: NULL | E61: NULL | F61: S005 | G61: Southeast | H61: 5 | I61: 0.2 | J61: 792 | K61: CASH | M61: NULL
A62: 61 | B62: P008 | C62: 45647 | D62: Denim Jacket | E62: GAP | F62: S005 | G62: Southeast | H62: 1 | I62: 0 | J62: 89.95 | K62: APPLE PAY | L62: James T. | M62: TRUE
A63: 62 | B63: P006 | C63: 45626 | D63: Floral Midi Dress | E63: Banana Republic | F63: S003 | G63: Midwest | H63: 2 | I63: 0 | J63: 159.9 | K63: PAYPAL | L63: Priya M. | M63: FALSE
A64: 63 | B64: P018 | C64: 45528 | D64: Rain Jacket | E64: Old Navy | F64: S005 | G64: Southeast | H64: 2 | I64: 0 | J64: 170 | K64: CASH | L64: Tom B. | M64: 1
A65: 64 | B65: P019 | C65: 45332 | D65: Slip-On Loafers | E65: GAP | G65: NULL | H65: 3 | I65: 0.1 | J65: 215.87 | K65: APPLE PAY | L65: Maria S. | M65: Yes
A66: 65 | B66: P020 | C66: 45183 | D66: Crossbody Bag | E66: Banana Republic | F66: S004 | G66: South | H66: 3 | I66: 0.05 | J66: 170.86 | K66: PAYPAL | M66: Yes
A67: 66 | B67: P019 | C67: 45261 | D67: Slip-On Loafers | E67: GAP | F67: S001 | G67: Northeast | H67: 3 | I67: 0 | J67: 239.85 | K67: CASH | L67: James T. | M67: Yes
A68: 67 | B68: P010 | C68: 45071 | D68: High-Rise Jeans | E68: GAP | F68: S008 | H68: 3 | I68: 0 | J68: 209.85 | K68: CREDIT CARD | L68: Tom B. | M68: 0
A69: 68 | B69: P012 | C69: 45618 | D69: Ankle Boots | E69: Banana Republic | F69: S008 | H69: 3 | I69: 0.2 | J69: 285.6 | K69: CREDIT CARD | L69: David N. | M69: FALSE
A70: 69 | B70: P014 | C70: 45238 | D70: Wrap Dress | E70: Intermix | F70: S005 | G70: Southeast | H70: 1 | I70: 0 | J70: 89.95 | K70: CREDIT CARD | L70: Maria S. | M70: Yes
A71: 70 | B71: P014 | C71: 44960 | D71: Wrap Dress | E71: Intermix | F71: S003 | G71: Midwest | H71: 1 | I71: 0.25 | J71: 67.46 | K71: CASH | L71: Priya M. | M71: Yes
A72: 71 | B72: P002 | C72: 45392 | D72: Slim Chino Pants | E72: GAP | F72: S006 | G72: West | H72: 4 | I72: n/a | J72: 239.8 | K72: CREDIT CARD | L72: Carlos R. | M72: 1
A73: 72 | B73: P019 | C73: 45537 | D73: Slip-On Loafers | E73: GAP | F73: S004 | G73: South | H73: 2 | I73: 0.05 | J73: 151.9 | K73: DEBIT CARD | L73: David N. | M73: Yes
A74: 73 | B74: P008 | C74: 45198 | D74: Denim Jacket | E74: GAP | F74: S006 | G74: West | H74: 5 | I74: 0.15 | J74: 382.29 | K74: DEBIT CARD | L74: Maria S. | M74: TRUE
A75: 74 | B75: P020 | C75: 44958 | D75: Crossbody Bag | E75: Banana Republic | F75: S004 | G75: South | H75: 1 | I75: 0.1 | J75: 53.96 | K75: APPLE PAY | L75: Tom B. | M75: Yes
A76: 75 | B76: P003 | C76: 45538 | D76: puffer jacket | E76: GAP | F76: S003 | G76: Midwest | H76: 2 | I76: 0.1 | J76: 232.2 | K76: GIFT CARD | L76: David N. | M76: TRUE
A77: 76 | B77: P014 | C77: 45391 | D77: Wrap Dress | E77: Intermix | F77: S004 | G77: South | H77: 4 | I77: 0.05 | J77: 341.81 | K77: CASH | L77: Priya M. | M77: Yes
A78: 77 | B78: P003 | C78: 45308 | D78: puffer jacket | E78: GAP | F78: S002 | G78: West | H78: 1 | I78: 0 | J78: 129 | K78: CREDIT CARD | L78: Priya M. | M78: TRUE
A79: 78 | B79: P010 | C79: 45518 | D79: High-Rise Jeans | E79: GAP | F79: S001 | G79: Northeast | H79: 5 | I79: 0.1 | J79: 314.78 | K79: CREDIT CARD | L79: David N. | M79: 0
A80: 79 | B80: P018 | C80: 45111 | D80: Rain Jacket | E80: Old Navy | F80: S007 | G80: Northeast | H80: 5 | J80: 425 | K80: CREDIT CARD | L80: Amy K. | M80: 1
A81: 80 | B81: P003 | C81: 45391 | D81: puffer jacket | E81: GAP | F81: S001 | G81: Northeast | H81: 5 | I81: 0.05 | J81: 612.75 | K81: GIFT CARD | L81: Priya M. | M81: TRUE
A82: 81 | B82: P003 | C82: 45548 | D82: puffer jacket | E82: GAP | F82: S001 | G82: Northeast | H82: 3 | I82: 0.25 | J82: 290.25 | K82: GIFT CARD | L82: Priya M. | M82: TRUE
A83: 82 | B83: P002 | C83: 45136 | D83: Slim Chino Pants | E83: GAP | F83: S005 | G83: Southeast | H83: 2 | I83: 0.2 | J83: 95.92 | K83: CREDIT CARD | L83: Maria S. | M83: 1
A84: 83 | B84: P017 | C84: 44970 | D84: Cargo Shorts | E84: Old Navy | G84: NULL | H84: 5 | I84: 0.15 | J84: 169.79 | K84: GIFT CARD | L84: James T. | M84: 1
A85: 84 | B85: P011 | C85: 45374 | D85: Trench Coat | E85: Banana Republic | F85: S001 | G85: Northeast | H85: 2 | I85: 0.25 | J85: 297 | K85: CREDIT CARD | L85: David N. | M85: FALSE
A86: 85 | B86: P017 | C86: 45587 | D86: Cargo Shorts | E86: Old Navy | F86: S002 | G86: West | H86: 5 | I86: 0.05 | J86: 189.76 | K86: CASH | L86: David N. | M86: 1
A87: 86 | B87: P015 | C87: 45250 | D87: Sports Bra | E87: Athleta | F87: S008 | H87: 5 | I87: 0.25 | J87: 168.56 | K87: APPLE PAY | L87: David N. | M87: TRUE
A88: 87 | B88: P002 | C88: 45019 | D88: NULL | E88: NULL | F88: S001 | G88: Northeast | H88: 3 | I88: 0.1 | J88: 161.87 | K88: APPLE PAY | L88: James T. | M88: NULL
A89: 88 | B89: P011 | C89: 45388 | D89: NULL | E89: NULL | F89: S004 | G89: South | H89: 5 | I89: 0.25 | J89: 742.5 | K89: CREDIT CARD | L89: Lin W. | M89: NULL
A90: 89 | B90: P012 | C90: 45273 | D90: Ankle Boots | E90: Banana Republic | F90: S003 | G90: Midwest | H90: 3 | I90: 0.1 | J90: 321.3 | K90: GIFT CARD | L90: Priya M. | M90: FALSE
A91: 90 | B91: P011 | C91: 45598 | D91: Trench Coat | E91: Banana Republic | F91: S003 | G91: Midwest | H91: 1 | I91: 0 | J91: 198 | K91: CASH | L91: David N. | M91: FALSE
A92: 91 | B92: P017 | C92: 45298 | D92: Cargo Shorts | E92: Old Navy | F92: S003 | G92: Midwest | H92: 1 | I92: 0.2 | J92: 31.96 | K92: CREDIT CARD | L92: David N. | M92: 1
A93: 92 | B93: P017 | C93: 45061 | D93: Cargo Shorts | E93: Old Navy | F93: S002 | G93: West | H93: 5 | I93: 0 | J93: 199.75 | K93: PAYPAL | L93: David N. | M93: 1
A94: 93 | B94: P015 | C94: 45473 | D94: Sports Bra | E94: Athleta | F94: S004 | G94: South | H94: 5 | I94: 0.1 | J94: 202.28 | K94: DEBIT CARD | L94: Tom B. | M94: TRUE
A95: 94 | B95: P013 | C95: 45546 | D95: Silk Scarf | E95: Intermix | F95: S005 | G95: Southeast | H95: 5 | I95: 0.2 | J95: 179.8 | K95: DEBIT CARD | L95: Lin W. | M95: No
A96: 95 | B96: P010 | C96: 45452 | D96: High-Rise Jeans | E96: GAP | F96: S002 | G96: West | H96: 1 | I96: 0 | J96: 69.95 | K96: GIFT CARD | L96: Amy K. | M96: 0
A97: 96 | B97: P017 | C97: 45310 | D97: Cargo Shorts | E97: Old Navy | G97: NULL | H97: 3 | I97: 0.05 | J97: 113.86 | K97: CREDIT CARD | L97: Priya M. | M97: 1
A98: 97 | B98: P016 | C98: 45189 | D98: Graphic Hoodie | E98: Old Navy | F98: S003 | G98: Midwest | H98: 4 | I98: 0 | J98: 199.8 | K98: CREDIT CARD | L98: James T. | M98: 0
A99: 98 | B99: P020 | C99: 45538 | D99: Crossbody Bag | E99: Banana Republic | G99: NULL | H99: 4 | I99: 0 | J99: 239.8 | K99: GIFT CARD | L99: James T. | M99: Yes
A100: 99 | B100: P017 | C100: 45408 | D100: Cargo Shorts | E100: Old Navy | F100: S002 | G100: West | H100: 3 | I100: 0 | J100: 119.85 | K100: GIFT CARD | L100: Maria S. | M100: 1
...

Sheet Cleaned Data
A1: transaction_id | B1: product_id | C1: sale_date | D1: product_name | E1: brand | F1: store_id | G1: region | H1: quantity | I1: discount | J1: total | K1: payment_method | L1: sales_rep | M1: is_active
A2: 1 | B2: P001 | C2: 45031 | D2: Classic Crew-Neck Tee | E2: GAP | F2: S002 | G2: West | H2: 3 | I2: 0 | J2: 59.97 | K2: =PROPER('Original Data'!K2) -> Debit Card | M2: {=_xlfn.IFS(OR('Original Data'!M2=0,'Original Data'!M2="No",'Original Data'!M2=FALSE),"No",OR('Original Data'!M2=1,'Original Data'!M2="Yes",'Original Data'!M2=TRUE),"Yes")} -> No
A3: 2 | B3: P008 | C3: 45641 | D3: Denim Jacket | E3: GAP | F3: S007 | G3: Northeast | H3: 4 | I3: 0.1 | J3: 323.82 | K3: =PROPER('Original Data'!K3) -> Debit Card | L3: Maria S. | M3: {=_xlfn.IFS(OR('Original Data'!M3=0,'Original Data'!M3="No",'Original Data'!M3=FALSE),"No",OR('Original Data'!M3=1,'Original Data'!M3="Yes",'Original Data'!M3=TRUE),"Yes")} -> Yes
A4: 3 | B4: P015 | C4: 45492 | D4: =VLOOKUP(B4,'Original Data'!B:D,3,FALSE) -> NULL | E4: =_xlfn.XLOOKUP('Cleaned Data'!B823,'Original Data'!B:B,'Original Data'!E:E) -> Banana Republic | F4: S001 | G4: Northeast | H4: 5 | I4: 0 | J4: 224.75 | K4: =PROPER('Original Data'!K4) -> Credit Card | L4: Priya M. | M4: Unknown
A5: 4 | B5: P008 | C5: 45577 | D5: =VLOOKUP(B5,'Original Data'!B:D,3,FALSE) -> Denim Jacket | E5: =_xlfn.XLOOKUP('Cleaned Data'!B407,'Original Data'!B:B,'Original Data'!E:E) -> Athleta | F5: S002 | G5: West | H5: 1 | I5: 0.2 | J5: 71.96 | K5: =PROPER('Original Data'!K5) -> Gift Card | L5: Amy K. | M5: Unknown
A6: 5 | B6: P006 | C6: 45631 | D6: Floral Midi Dress | E6: Banana Republic | F6: S004 | G6: South | H6: 4 | I6: 0 | J6: 319.8 | K6: =PROPER('Original Data'!K6) -> Apple Pay | M6: {=_xlfn.IFS(OR('Original Data'!M6=0,'Original Data'!M6="No",'Original Data'!M6=FALSE),"No",OR('Original Data'!M6=1,'Original Data'!M6="Yes",'Original Data'!M6=TRUE),"Yes")} -> No
A7: 6 | B7: P007 | C7: 45198 | D7: Running Leggings | E7: Athleta | F7: S006 | G7: West | H7: 4 | I7: 0.2 | J7: 207.84 | K7: =PROPER('Original Data'!K7) -> Debit Card | L7: Tom B. | M7: {=_xlfn.IFS(OR('Original Data'!M7=0,'Original Data'!M7="No",'Original Data'!M7=FALSE),"No",OR('Original Data'!M7=1,'Original Data'!M7="Yes",'Original Data'!M7=TRUE),"Yes")} -> Yes
A8: 7 | B8: P003 | C8: 45090 | D8: Puffer Jacket | E8: GAP | F8: S008 | H8: 1 | I8: 0 | J8: 129 | K8: =PROPER('Original Data'!K8) -> Apple Pay | L8: Lin W. | M8: {=_xlfn.IFS(OR('Original Data'!M8=0,'Original Data'!M8="No",'Original Data'!M8=FALSE),"No",OR('Original Data'!M8=1,'Original Data'!M8="Yes",'Original Data'!M8=TRUE),"Yes")} -> Yes
A9: 8 | B9: P004 | C9: 45227 | D9: Canvas Sneakers | E9: Old Navy | F9: S001 | G9: Northeast | H9: 5 | I9: 0.1 | J9: 224.78 | K9: =PROPER('Original Data'!K9) -> Credit Card | L9: David N. | M9: {=_xlfn.IFS(OR('Original Data'!M9=0,'Original Data'!M9="No",'Original Data'!M9=FALSE),"No",OR('Original Data'!M9=1,'Original Data'!M9="Yes",'Original Data'!M9=TRUE),"Yes")} -> No
A10: 9 | B10: P010 | C10: 45092 | D10: High-Rise Jeans | E10: GAP | F10: S002 | G10: West | H10: 5 | I10: 0.05 | J10: 332.26 | K10: =PROPER('Original Data'!K10) -> Cash | L10: Lin W. | M10: {=_xlfn.IFS(OR('Original Data'!M10=0,'Original Data'!M10="No",'Original Data'!M10=FALSE),"No",OR('Original Data'!M10=1,'Original Data'!M10="Yes",'Original Data'!M10=TRUE),"Yes")} -> No
A11: 10 | B11: P008 | C11: 45424 | D11: Denim Jacket | E11: GAP | F11: S005 | G11: Southeast | H11: 1 | I11: 0.05 | J11: 85.45 | K11: =PROPER('Original Data'!K11) -> Credit Card | L11: James T. | M11: {=_xlfn.IFS(OR('Original Data'!M11=0,'Original Data'!M11="No",'Original Data'!M11=FALSE),"No",OR('Original Data'!M11=1,'Original Data'!M11="Yes",'Original Data'!M11=TRUE),"Yes")} -> Yes
A12: 11 | B12: P018 | C12: 45592 | D12: Rain Jacket | E12: Old Navy | F12: S004 | G12: South | H12: 2 | I12: 0.1 | J12: 153 | K12: =PROPER('Original Data'!K12) -> Apple Pay | L12: Priya M. | M12: {=_xlfn.IFS(OR('Original Data'!M12=0,'Original Data'!M12="No",'Original Data'!M12=FALSE),"No",OR('Original Data'!M12=1,'Original Data'!M12="Yes",'Original Data'!M12=TRUE),"Yes")} -> Yes
A13: 12 | B13: P002 | C13: 44999 | D13: Slim Chino Pants | E13: GAP | F13: S002 | G13: West | H13: 2 | I13: 0 | J13: 119.9 | K13: =PROPER('Original Data'!K13) -> Cash | L13: Maria S. | M13: {=_xlfn.IFS(OR('Original Data'!M13=0,'Original Data'!M13="No",'Original Data'!M13=FALSE),"No",OR('Original Data'!M13=1,'Original Data'!M13="Yes",'Original Data'!M13=TRUE),"Yes")} -> Yes
A14: 13 | B14: P007 | C14: 45360 | D14: Running Leggings | E14: Athleta | F14: S007 | G14: Northeast | H14: 1 | I14: 0 | J14: 64.95 | K14: =PROPER('Original Data'!K14) -> Cash | L14: Priya M. | M14: {=_xlfn.IFS(OR('Original Data'!M14=0,'Original Data'!M14="No",'Original Data'!M14=FALSE),"No",OR('Original Data'!M14=1,'Original Data'!M14="Yes",'Original Data'!M14=TRUE),"Yes")} -> Yes
A15: 14 | B15: P007 | C15: 45114 | D15: Running Leggings | E15: Athleta | F15: S004 | G15: South | H15: 2 | I15: 0.25 | J15: 97.43 | K15: =PROPER('Original Data'!K15) -> Gift Card | L15: Lin W. | M15: {=_xlfn.IFS(OR('Original Data'!M15=0,'Original Data'!M15="No",'Original Data'!M15=FALSE),"No",OR('Original Data'!M15=1,'Original Data'!M15="Yes",'Original Data'!M15=TRUE),"Yes")} -> Yes
A16: 15 | B16: P003 | C16: 45419 | D16: Puffer Jacket | E16: GAP | F16: S001 | G16: Northeast | H16: 2 | I16: 0 | J16: 258 | K16: =PROPER('Original Data'!K16) -> Gift Card | L16: Priya M. | M16: {=_xlfn.IFS(OR('Original Data'!M16=0,'Original Data'!M16="No",'Original Data'!M16=FALSE),"No",OR('Original Data'!M16=1,'Original Data'!M16="Yes",'Original Data'!M16=TRUE),"Yes")} -> Yes
A17: 16 | B17: P005 | C17: 45520 | D17: Leather Belt | E17: Banana Republic | F17: S008 | H17: 2 | I17: 0.1 | J17: 62.98 | K17: =PROPER('Original Data'!K17) -> Credit Card | L17: Carlos R. | M17: {=_xlfn.IFS(OR('Original Data'!M17=0,'Original Data'!M17="No",'Original Data'!M17=FALSE),"No",OR('Original Data'!M17=1,'Original Data'!M17="Yes",'Original Data'!M17=TRUE),"Yes")} -> No
A18: 17 | B18: P006 | C18: 45049 | D18: Floral Midi Dress | E18: Banana Republic | F18: S002 | G18: West | H18: 1 | I18: 0 | J18: 79.95 | K18: =PROPER('Original Data'!K18) -> Gift Card | L18: Carlos R. | M18: {=_xlfn.IFS(OR('Original Data'!M18=0,'Original Data'!M18="No",'Original Data'!M18=FALSE),"No",OR('Original Data'!M18=1,'Original Data'!M18="Yes",'Original Data'!M18=TRUE),"Yes")} -> No
A19: 18 | B19: P008 | C19: 45587 | D19: Denim Jacket | E19: GAP | F19: S006 | G19: West | H19: 3 | I19: 0 | J19: 269.85 | K19: =PROPER('Original Data'!K19) -> Apple Pay | L19: Lin W. | M19: {=_xlfn.IFS(OR('Original Data'!M19=0,'Original Data'!M19="No",'Original Data'!M19=FALSE),"No",OR('Original Data'!M19=1,'Original Data'!M19="Yes",'Original Data'!M19=TRUE),"Yes")} -> Yes
A20: 19 | B20: P008 | C20: 45483 | D20: Denim Jacket | E20: GAP | F20: S002 | G20: West | H20: 3 | I20: 0.1 | J20: 242.87 | K20: =PROPER('Original Data'!K20) -> Gift Card | L20: Lin W. | M20: {=_xlfn.IFS(OR('Original Data'!M20=0,'Original Data'!M20="No",'Original Data'!M20=FALSE),"No",OR('Original Data'!M20=1,'Original Data'!M20="Yes",'Original Data'!M20=TRUE),"Yes")} -> Yes
A21: 20 | B21: P009 | C21: 45215 | D21: Wool Sweater | E21: Banana Republic | F21: S003 | G21: Midwest | H21: 1 | I21: 0 | J21: 74.95 | K21: =PROPER('Original Data'!K21) -> Cash | L21: Lin W. | M21: {=_xlfn.IFS(OR('Original Data'!M21=0,'Original Data'!M21="No",'Original Data'!M21=FALSE),"No",OR('Original Data'!M21=1,'Original Data'!M21="Yes",'Original Data'!M21=TRUE),"Yes")} -> No
A22: 21 | B22: P009 | C22: 45579 | D22: Wool Sweater | E22: Banana Republic | F22: S007 | G22: Northeast | H22: 1 | I22: 0 | J22: 74.95 | K22: =PROPER('Original Data'!K22) -> Debit Card | L22: David N. | M22: {=_xlfn.IFS(OR('Original Data'!M22=0,'Original Data'!M22="No",'Original Data'!M22=FALSE),"No",OR('Original Data'!M22=1,'Original Data'!M22="Yes",'Original Data'!M22=TRUE),"Yes")} -> No
A23: 22 | B23: P012 | C23: 44969 | D23: Ankle Boots | E23: Banana Republic | F23: S001 | G23: Northeast | H23: 5 | I23: 0 | J23: 595 | K23: =PROPER('Original Data'!K23) -> Debit Card | L23: Priya M. | M23: {=_xlfn.IFS(OR('Original Data'!M23=0,'Original Data'!M23="No",'Original Data'!M23=FALSE),"No",OR('Original Data'!M23=1,'Original Data'!M23="Yes",'Original Data'!M23=TRUE),"Yes")} -> No
A24: 23 | B24: P020 | C24: 45349 | D24: Crossbody Bag | E24: Banana Republic | F24: S007 | G24: Northeast | H24: 2 | I24: 0.05 | J24: 113.9 | K24: =PROPER('Original Data'!K24) -> Debit Card | L24: Lin W. | M24: {=_xlfn.IFS(OR('Original Data'!M24=0,'Original Data'!M24="No",'Original Data'!M24=FALSE),"No",OR('Original Data'!M24=1,'Original Data'!M24="Yes",'Original Data'!M24=TRUE),"Yes")} -> Yes
A25: 24 | B25: P013 | C25: 45398 | D25: Silk Scarf | E25: Intermix | F25: S002 | G25: West | H25: 1 | J25: 44.95 | K25: =PROPER('Original Data'!K25) -> Debit Card | M25: {=_xlfn.IFS(OR('Original Data'!M25=0,'Original Data'!M25="No",'Original Data'!M25=FALSE),"No",OR('Original Data'!M25=1,'Original Data'!M25="Yes",'Original Data'!M25=TRUE),"Yes")} -> No
A26: 25 | B26: P017 | C26: 45194 | D26: Cargo Shorts | E26: Old Navy | F26: S006 | G26: West | H26: 4 | I26: 0.15 | J26: 135.83 | K26: =PROPER('Original Data'!K26) -> Credit Card | L26: Maria S. | M26: {=_xlfn.IFS(OR('Original Data'!M26=0,'Original Data'!M26="No",'Original Data'!M26=FALSE),"No",OR('Original Data'!M26=1,'Original Data'!M26="Yes",'Original Data'!M26=TRUE),"Yes")} -> Yes
A27: 26 | B27: P013 | C27: 45652 | D27: Silk Scarf | E27: Intermix | G27: NULL | H27: 5 | I27: 0.05 | J27: 213.51 | K27: =PROPER('Original Data'!K27) -> Credit Card | L27: Amy K. | M27: {=_xlfn.IFS(OR('Original Data'!M27=0,'Original Data'!M27="No",'Original Data'!M27=FALSE),"No",OR('Original Data'!M27=1,'Original Data'!M27="Yes",'Original Data'!M27=TRUE),"Yes")} -> No
A28: 27 | B28: P020 | C28: 45243 | D28: Crossbody Bag | E28: Banana Republic | F28: S006 | G28: West | H28: 3 | I28: 0 | J28: 179.85 | K28: PayPal | L28: Amy K. | M28: {=_xlfn.IFS(OR('Original Data'!M28=0,'Original Data'!M28="No",'Original Data'!M28=FALSE),"No",OR('Original Data'!M28=1,'Original Data'!M28="Yes",'Original Data'!M28=TRUE),"Yes")} -> Yes
A29: 28 | B29: P013 | C29: 45142 | D29: Silk Scarf | E29: Intermix | F29: S005 | G29: Southeast | H29: 5 | I29: 0 | J29: 224.75 | K29: =PROPER('Original Data'!K29) -> Cash | L29: Amy K. | M29: {=_xlfn.IFS(OR('Original Data'!M29=0,'Original Data'!M29="No",'Original Data'!M29=FALSE),"No",OR('Original Data'!M29=1,'Original Data'!M29="Yes",'Original Data'!M29=TRUE),"Yes")} -> No
A30: 29 | B30: P003 | C30: 45615 | D30: Puffer Jacket | E30: GAP | F30: S003 | G30: Midwest | H30: 3 | I30: 0.15 | J30: 328.95 | K30: =PROPER('Original Data'!K30) -> Debit Card | L30: James T. | M30: {=_xlfn.IFS(OR('Original Data'!M30=0,'Original Data'!M30="No",'Original Data'!M30=FALSE),"No",OR('Original Data'!M30=1,'Original Data'!M30="Yes",'Original Data'!M30=TRUE),"Yes")} -> Yes
A31: 30 | B31: P013 | C31: 45598 | D31: Silk Scarf | E31: Intermix | G31: NULL | H31: 4 | I31: 0.2 | J31: 143.84 | K31: =PROPER('Original Data'!K31) -> Debit Card | L31: Carlos R. | M31: {=_xlfn.IFS(OR('Original Data'!M31=0,'Original Data'!M31="No",'Original Data'!M31=FALSE),"No",OR('Original Data'!M31=1,'Original Data'!M31="Yes",'Original Data'!M31=TRUE),"Yes")} -> No
A32: 31 | B32: P018 | C32: 45402 | D32: Rain Jacket | E32: Old Navy | F32: S001 | G32: Northeast | H32: 2 | I32: 0 | J32: 170 | K32: =PROPER('Original Data'!K32) -> Debit Card | L32: Tom B. | M32: {=_xlfn.IFS(OR('Original Data'!M32=0,'Original Data'!M32="No",'Original Data'!M32=FALSE),"No",OR('Original Data'!M32=1,'Original Data'!M32="Yes",'Original Data'!M32=TRUE),"Yes")} -> Yes
A33: 32 | B33: P006 | C33: 45579 | D33: Floral Midi Dress | E33: Banana Republic | F33: S008 | H33: 4 | I33: 0.25 | J33: 239.85 | K33: =PROPER('Original Data'!K33) -> Debit Card | L33: Amy K. | M33: {=_xlfn.IFS(OR('Original Data'!M33=0,'Original Data'!M33="No",'Original Data'!M33=FALSE),"No",OR('Original Data'!M33=1,'Original Data'!M33="Yes",'Original Data'!M33=TRUE),"Yes")} -> No
A34: 33 | B34: P005 | C34: 45083 | D34: Leather Belt | E34: Banana Republic | F34: S002 | G34: West | H34: 2 | I34: 0.05 | J34: 66.48 | K34: =PROPER('Original Data'!K34) -> Apple Pay | L34: Priya M. | M34: {=_xlfn.IFS(OR('Original Data'!M34=0,'Original Data'!M34="No",'Original Data'!M34=FALSE),"No",OR('Original Data'!M34=1,'Original Data'!M34="Yes",'Original Data'!M34=TRUE),"Yes")} -> No
A35: 34 | B35: P019 | C35: 45232 | D35: Slip-On Loafers | E35: GAP | F35: S001 | G35: Northeast | H35: 4 | I35: 0.25 | J35: 239.85 | K35: =PROPER('Original Data'!K35) -> Cash | L35: Maria S. | M35: {=_xlfn.IFS(OR('Original Data'!M35=0,'Original Data'!M35="No",'Original Data'!M35=FALSE),"No",OR('Original Data'!M35=1,'Original Data'!M35="Yes",'Original Data'!M35=TRUE),"Yes")} -> Yes
A36: 35 | B36: P016 | C36: 45622 | D36: Graphic Hoodie | E36: Old Navy | F36: S007 | G36: Northeast | H36: 1 | I36: 0.2 | J36: 39.96 | K36: =PROPER('Original Data'!K36) -> Apple Pay | L36: David N. | M36: {=_xlfn.IFS(OR('Original Data'!M36=0,'Original Data'!M36="No",'Original Data'!M36=FALSE),"No",OR('Original Data'!M36=1,'Original Data'!M36="Yes",'Original Data'!M36=TRUE),"Yes")} -> No
A37: 36 | B37: P014 | C37: 45193 | D37: Wrap Dress | E37: Intermix | F37: S002 | G37: West | H37: 2 | I37: 0.25 | J37: 134.93 | K37: =PROPER('Original Data'!K37) -> Credit Card | L37: Lin W. | M37: {=_xlfn.IFS(OR('Original Data'!M37=0,'Original Data'!M37="No",'Original Data'!M37=FALSE),"No",OR('Original Data'!M37=1,'Original Data'!M37="Yes",'Original Data'!M37=TRUE),"Yes")} -> Yes
A38: 37 | B38: P001 | C38: 45592 | D38: Classic Crew-Neck Tee | E38: GAP | F38: S008 | H38: 5 | I38: 0 | J38: 99.95 | K38: =PROPER('Original Data'!K38) -> Debit Card | L38: David N. | M38: Unknown
A39: 38 | B39: P019 | C39: 45098 | D39: Slip-On Loafers | E39: GAP | F39: S002 | G39: West | H39: 2 | I39: 0.25 | J39: 119.93 | K39: =PROPER('Original Data'!K39) -> Cash | M39: {=_xlfn.IFS(OR('Original Data'!M39=0,'Original Data'!M39="No",'Original Data'!M39=FALSE),"No",OR('Original Data'!M39=1,'Original Data'!M39="Yes",'Original Data'!M39=TRUE),"Yes")} -> Yes
A40: 39 | B40: P013 | C40: 45640 | D40: Silk Scarf | E40: Intermix | F40: S007 | G40: Northeast | H40: 2 | I40: 0 | J40: 89.9 | K40: =PROPER('Original Data'!K40) -> Credit Card | L40: Carlos R. | M40: {=_xlfn.IFS(OR('Original Data'!M40=0,'Original Data'!M40="No",'Original Data'!M40=FALSE),"No",OR('Original Data'!M40=1,'Original Data'!M40="Yes",'Original Data'!M40=TRUE),"Yes")} -> No
A41: 40 | B41: P001 | C41: 45297 | D41: Classic Crew-Neck Tee | E41: GAP | F41: S006 | G41: West | H41: 4 | I41: 0.25 | J41: 59.97 | K41: =PROPER('Original Data'!K41) -> Gift Card | L41: James T. | M41: {=_xlfn.IFS(OR('Original Data'!M41=0,'Original Data'!M41="No",'Original Data'!M41=FALSE),"No",OR('Original Data'!M41=1,'Original Data'!M41="Yes",'Original Data'!M41=TRUE),"Yes")} -> No
A42: 41 | B42: P015 | C42: 45015 | D42: =VLOOKUP(B42,'Original Data'!B:D,3,FALSE) -> NULL | E42: =_xlfn.XLOOKUP('Cleaned Data'!B824,'Original Data'!B:B,'Original Data'!E:E) -> Old Navy | F42: S008 | H42: 4 | I42: 0.1 | J42: 161.82 | K42: =PROPER('Original Data'!K42) -> Debit Card | L42: David N. | M42: Unknown
A43: 42 | B43: P012 | C43: 45645 | D43: Ankle Boots | E43: Banana Republic | F43: S004 | G43: South | H43: 3 | I43: 0.15 | J43: 303.45 | K43: PayPal | L43: Amy K. | M43: {=_xlfn.IFS(OR('Original Data'!M43=0,'Original Data'!M43="No",'Original Data'!M43=FALSE),"No",OR('Original Data'!M43=1,'Original Data'!M43="Yes",'Original Data'!M43=TRUE),"Yes")} -> No
A44: 43 | B44: P015 | C44: 45341 | D44: Sports Bra | E44: Athleta | F44: S008 | H44: 1 | I44: 0 | J44: 44.95 | K44: =PROPER('Original Data'!K44) -> Debit Card | L44: Amy K. | M44: {=_xlfn.IFS(OR('Original Data'!M44=0,'Original Data'!M44="No",'Original Data'!M44=FALSE),"No",OR('Original Data'!M44=1,'Original Data'!M44="Yes",'Original Data'!M44=TRUE),"Yes")} -> Yes
A45: 44 | B45: P009 | C45: 45124 | D45: Wool Sweater | E45: Banana Republic | F45: S008 | H45: 3 | I45: 0.1 | J45: 202.37 | K45: =PROPER('Original Data'!K45) -> Credit Card | L45: Carlos R. | M45: {=_xlfn.IFS(OR('Original Data'!M45=0,'Original Data'!M45="No",'Original Data'!M45=FALSE),"No",OR('Original Data'!M45=1,'Original Data'!M45="Yes",'Original Data'!M45=TRUE),"Yes")} -> No
A46: 45 | B46: P004 | C46: 45110 | D46: Canvas Sneakers | E46: Old Navy | G46: NULL | H46: 2 | I46: 0.1 | J46: 89.91 | K46: =PROPER('Original Data'!K46) -> Cash | L46: Carlos R. | M46: {=_xlfn.IFS(OR('Original Data'!M46=0,'Original Data'!M46="No",'Original Data'!M46=FALSE),"No",OR('Original Data'!M46=1,'Original Data'!M46="Yes",'Original Data'!M46=TRUE),"Yes")} -> No
A47: 46 | B47: P004 | C47: 45378 | D47: Canvas Sneakers | E47: Old Navy | F47: S008 | H47: 1 | I47: 0.1 | J47: 44.96 | K47: =PROPER('Original Data'!K47) -> Gift Card | L47: Tom B. | M47: {=_xlfn.IFS(OR('Original Data'!M47=0,'Original Data'!M47="No",'Original Data'!M47=FALSE),"No",OR('Original Data'!M47=1,'Original Data'!M47="Yes",'Original Data'!M47=TRUE),"Yes")} -> No
A48: 47 | B48: P005 | C48: 45048 | D48: Leather Belt | E48: Banana Republic | F48: S001 | G48: Northeast | H48: 2 | I48: 0.1 | J48: 62.98 | K48: =PROPER('Original Data'!K48) -> Debit Card | L48: James T. | M48: {=_xlfn.IFS(OR('Original Data'!M48=0,'Original Data'!M48="No",'Original Data'!M48=FALSE),"No",OR('Original Data'!M48=1,'Original Data'!M48="Yes",'Original Data'!M48=TRUE),"Yes")} -> No
A49: 48 | B49: P010 | C49: 45567 | D49: High-Rise Jeans | E49: GAP | F49: S007 | G49: Northeast | H49: 5 | I49: 0 | J49: 349.75 | K49: =PROPER('Original Data'!K49) -> Debit Card | L49: James T. | M49: {=_xlfn.IFS(OR('Original Data'!M49=0,'Original Data'!M49="No",'Original Data'!M49=FALSE),"No",OR('Original Data'!M49=1,'Original Data'!M49="Yes",'Original Data'!M49=TRUE),"Yes")} -> No
A50: 49 | B50: P010 | C50: 45216 | D50: High-Rise Jeans | E50: GAP | F50: S008 | H50: 1 | I50: 0.05 | J50: 66.45 | K50: =PROPER('Original Data'!K50) -> Apple Pay | L50: Amy K. | M50: {=_xlfn.IFS(OR('Original Data'!M50=0,'Original Data'!M50="No",'Original Data'!M50=FALSE),"No",OR('Original Data'!M50=1,'Original Data'!M50="Yes",'Original Data'!M50=TRUE),"Yes")} -> No
A51: 50 | B51: P014 | C51: 45072 | D51: Wrap Dress | E51: Intermix | F51: S004 | G51: South | H51: 1 | I51: 0.05 | J51: 85.45 | K51: =PROPER('Original Data'!K51) -> Cash | L51: Lin W. | M51: {=_xlfn.IFS(OR('Original Data'!M51=0,'Original Data'!M51="No",'Original Data'!M51=FALSE),"No",OR('Original Data'!M51=1,'Original Data'!M51="Yes",'Original Data'!M51=TRUE),"Yes")} -> Yes
A52: 51 | B52: P009 | C52: 45539 | D52: Wool Sweater | E52: Banana Republic | F52: S007 | G52: Northeast | H52: 5 | J52: 374.75 | K52: =PROPER('Original Data'!K52) -> Credit Card | L52: Tom B. | M52: {=_xlfn.IFS(OR('Original Data'!M52=0,'Original Data'!M52="No",'Original Data'!M52=FALSE),"No",OR('Original Data'!M52=1,'Original Data'!M52="Yes",'Original Data'!M52=TRUE),"Yes")} -> No
A53: 52 | B53: P019 | C53: 45594 | D53: Slip-On Loafers | E53: GAP | F53: S005 | G53: Southeast | H53: 1 | I53: 0 | J53: 79.95 | K53: PayPal | L53: Tom B. | M53: {=_xlfn.IFS(OR('Original Data'!M53=0,'Original Data'!M53="No",'Original Data'!M53=FALSE),"No",OR('Original Data'!M53=1,'Original Data'!M53="Yes",'Original Data'!M53=TRUE),"Yes")} -> Yes
A54: 53 | B54: P006 | C54: 45605 | D54: Floral Midi Dress | E54: Banana Republic | F54: S002 | G54: West | H54: 3 | I54: 0.2 | J54: 191.88 | K54: =PROPER('Original Data'!K54) -> Cash | L54: Tom B. | M54: {=_xlfn.IFS(OR('Original Data'!M54=0,'Original Data'!M54="No",'Original Data'!M54=FALSE),"No",OR('Original Data'!M54=1,'Original Data'!M54="Yes",'Original Data'!M54=TRUE),"Yes")} -> No
A55: 54 | B55: P018 | C55: 45457 | D55: Rain Jacket | E55: Old Navy | F55: S001 | G55: Northeast | H55: 4 | I55: 0 | J55: 340 | K55: =PROPER('Original Data'!K55) -> Debit Card | L55: Maria S. | M55: {=_xlfn.IFS(OR('Original Data'!M55=0,'Original Data'!M55="No",'Original Data'!M55=FALSE),"No",OR('Original Data'!M55=1,'Original Data'!M55="Yes",'Original Data'!M55=TRUE),"Yes")} -> Yes
A56: 55 | B56: P001 | C56: 45491 | D56: Classic Crew-Neck Tee | E56: GAP | F56: S002 | G56: West | H56: 5 | I56: 0.05 | J56: 94.95 | K56: =PROPER('Original Data'!K56) -> Cash | L56: Lin W. | M56: {=_xlfn.IFS(OR('Original Data'!M56=0,'Original Data'!M56="No",'Original Data'!M56=FALSE),"No",OR('Original Data'!M56=1,'Original Data'!M56="Yes",'Original Data'!M56=TRUE),"Yes")} -> No
A57: 56 | B57: P010 | C57: 45410 | D57: High-Rise Jeans | E57: GAP | F57: S008 | H57: 5 | I57: 0.1 | J57: 314.78 | K57: =PROPER('Original Data'!K57) -> Gift Card | L57: Priya M. | M57: {=_xlfn.IFS(OR('Original Data'!M57=0,'Original Data'!M57="No",'Original Data'!M57=FALSE),"No",OR('Original Data'!M57=1,'Original Data'!M57="Yes",'Original Data'!M57=TRUE),"Yes")} -> No
A58: 57 | B58: P011 | C58: 45232 | D58: Trench Coat | E58: Banana Republic | F58: S007 | G58: Northeast | H58: 5 | I58: 0.1 | J58: 891 | K58: =PROPER('Original Data'!K58) -> Cash | L58: Maria S. | M58: {=_xlfn.IFS(OR('Original Data'!M58=0,'Original Data'!M58="No",'Original Data'!M58=FALSE),"No",OR('Original Data'!M58=1,'Original Data'!M58="Yes",'Original Data'!M58=TRUE),"Yes")} -> No
A59: 58 | B59: P007 | C59: 44971 | D59: Running Leggings | E59: Athleta | F59: S006 | G59: West | H59: 2 | I59: 0.2 | J59: 103.92 | K59: =PROPER('Original Data'!K59) -> Gift Card | L59: Carlos R. | M59: {=_xlfn.IFS(OR('Original Data'!M59=0,'Original Data'!M59="No",'Original Data'!M59=FALSE),"No",OR('Original Data'!M59=1,'Original Data'!M59="Yes",'Original Data'!M59=TRUE),"Yes")} -> Yes
A60: 59 | B60: P005 | C60: 45029 | D60: Leather Belt | E60: Banana Republic | F60: S001 | G60: Northeast | H60: 5 | I60: 0.15 | J60: 148.71 | K60: =PROPER('Original Data'!K60) -> Gift Card | L60: James T. | M60: {=_xlfn.IFS(OR('Original Data'!M60=0,'Original Data'!M60="No",'Original Data'!M60=FALSE),"No",OR('Original Data'!M60=1,'Original Data'!M60="Yes",'Original Data'!M60=TRUE),"Yes")} -> No
A61: 60 | B61: P011 | C61: 45617 | D61: =VLOOKUP(B61,'Original Data'!B:D,3,FALSE) -> Trench Coat | E61: =_xlfn.XLOOKUP('Cleaned Data'!B589,'Original Data'!B:B,'Original Data'!E:E) -> Old Navy | F61: S005 | G61: Southeast | H61: 5 | I61: 0.2 | J61: 792 | K61: =PROPER('Original Data'!K61) -> Cash | M61: Unknown
A62: 61 | B62: P008 | C62: 45647 | D62: Denim Jacket | E62: GAP | F62: S005 | G62: Southeast | H62: 1 | I62: 0 | J62: 89.95 | K62: =PROPER('Original Data'!K62) -> Apple Pay | L62: James T. | M62: {=_xlfn.IFS(OR('Original Data'!M62=0,'Original Data'!M62="No",'Original Data'!M62=FALSE),"No",OR('Original Data'!M62=1,'Original Data'!M62="Yes",'Original Data'!M62=TRUE),"Yes")} -> Yes
A63: 62 | B63: P006 | C63: 45626 | D63: Floral Midi Dress | E63: Banana Republic | F63: S003 | G63: Midwest | H63: 2 | I63: 0 | J63: 159.9 | K63: PayPal | L63: Priya M. | M63: {=_xlfn.IFS(OR('Original Data'!M63=0,'Original Data'!M63="No",'Original Data'!M63=FALSE),"No",OR('Original Data'!M63=1,'Original Data'!M63="Yes",'Original Data'!M63=TRUE),"Yes")} -> No
A64: 63 | B64: P018 | C64: 45528 | D64: Rain Jacket | E64: Old Navy | F64: S005 | G64: Southeast | H64: 2 | I64: 0 | J64: 170 | K64: =PROPER('Original Data'!K64) -> Cash | L64: Tom B. | M64: {=_xlfn.IFS(OR('Original Data'!M64=0,'Original Data'!M64="No",'Original Data'!M64=FALSE),"No",OR('Original Data'!M64=1,'Original Data'!M64="Yes",'Original Data'!M64=TRUE),"Yes")} -> Yes
A65: 64 | B65: P019 | C65: 45332 | D65: Slip-On Loafers | E65: GAP | G65: NULL | H65: 3 | I65: 0.1 | J65: 215.87 | K65: =PROPER('Original Data'!K65) -> Apple Pay | L65: Maria S. | M65: {=_xlfn.IFS(OR('Original Data'!M65=0,'Original Data'!M65="No",'Original Data'!M65=FALSE),"No",OR('Original Data'!M65=1,'Original Data'!M65="Yes",'Original Data'!M65=TRUE),"Yes")} -> Yes
A66: 65 | B66: P020 | C66: 45183 | D66: Crossbody Bag | E66: Banana Republic | F66: S004 | G66: South | H66: 3 | I66: 0.05 | J66: 170.86 | K66: PayPal | M66: {=_xlfn.IFS(OR('Original Data'!M66=0,'Original Data'!M66="No",'Original Data'!M66=FALSE),"No",OR('Original Data'!M66=1,'Original Data'!M66="Yes",'Original Data'!M66=TRUE),"Yes")} -> Yes
A67: 66 | B67: P019 | C67: 45261 | D67: Slip-On Loafers | E67: GAP | F67: S001 | G67: Northeast | H67: 3 | I67: 0 | J67: 239.85 | K67: =PROPER('Original Data'!K67) -> Cash | L67: James T. | M67: {=_xlfn.IFS(OR('Original Data'!M67=0,'Original Data'!M67="No",'Original Data'!M67=FALSE),"No",OR('Original Data'!M67=1,'Original Data'!M67="Yes",'Original Data'!M67=TRUE),"Yes")} -> Yes
A68: 67 | B68: P010 | C68: 45071 | D68: High-Rise Jeans | E68: GAP | F68: S008 | H68: 3 | I68: 0 | J68: 209.85 | K68: =PROPER('Original Data'!K68) -> Credit Card | L68: Tom B. | M68: {=_xlfn.IFS(OR('Original Data'!M68=0,'Original Data'!M68="No",'Original Data'!M68=FALSE),"No",OR('Original Data'!M68=1,'Original Data'!M68="Yes",'Original Data'!M68=TRUE),"Yes")} -> No
A69: 68 | B69: P012 | C69: 45618 | D69: Ankle Boots | E69: Banana Republic | F69: S008 | H69: 3 | I69: 0.2 | J69: 285.6 | K69: =PROPER('Original Data'!K69) -> Credit Card | L69: David N. | M69: {=_xlfn.IFS(OR('Original Data'!M69=0,'Original Data'!M69="No",'Original Data'!M69=FALSE),"No",OR('Original Data'!M69=1,'Original Data'!M69="Yes",'Original Data'!M69=TRUE),"Yes")} -> No
A70: 69 | B70: P014 | C70: 45238 | D70: Wrap Dress | E70: Intermix | F70: S005 | G70: Southeast | H70: 1 | I70: 0 | J70: 89.95 | K70: =PROPER('Original Data'!K70) -> Credit Card | L70: Maria S. | M70: {=_xlfn.IFS(OR('Original Data'!M70=0,'Original Data'!M70="No",'Original Data'!M70=FALSE),"No",OR('Original Data'!M70=1,'Original Data'!M70="Yes",'Original Data'!M70=TRUE),"Yes")} -> Yes
A71: 70 | B71: P014 | C71: 44960 | D71: Wrap Dress | E71: Intermix | F71: S003 | G71: Midwest | H71: 1 | I71: 0.25 | J71: 67.46 | K71: =PROPER('Original Data'!K71) -> Cash | L71: Priya M. | M71: {=_xlfn.IFS(OR('Original Data'!M71=0,'Original Data'!M71="No",'Original Data'!M71=FALSE),"No",OR('Original Data'!M71=1,'Original Data'!M71="Yes",'Original Data'!M71=TRUE),"Yes")} -> Yes
A72: 71 | B72: P002 | C72: 45392 | D72: Slim Chino Pants | E72: GAP | F72: S006 | G72: West | H72: 4 | I72: 0 | J72: 239.8 | K72: =PROPER('Original Data'!K72) -> Credit Card | L72: Carlos R. | M72: {=_xlfn.IFS(OR('Original Data'!M72=0,'Original Data'!M72="No",'Original Data'!M72=FALSE),"No",OR('Original Data'!M72=1,'Original Data'!M72="Yes",'Original Data'!M72=TRUE),"Yes")} -> Yes
A73: 72 | B73: P019 | C73: 45537 | D73: Slip-On Loafers | E73: GAP | F73: S004 | G73: South | H73: 2 | I73: 0.05 | J73: 151.9 | K73: =PROPER('Original Data'!K73) -> Debit Card | L73: David N. | M73: {=_xlfn.IFS(OR('Original Data'!M73=0,'Original Data'!M73="No",'Original Data'!M73=FALSE),"No",OR('Original Data'!M73=1,'Original Data'!M73="Yes",'Original Data'!M73=TRUE),"Yes")} -> Yes
A74: 73 | B74: P008 | C74: 45198 | D74: Denim Jacket | E74: GAP | F74: S006 | G74: West | H74: 5 | I74: 0.15 | J74: 382.29 | K74: =PROPER('Original Data'!K74) -> Debit Card | L74: Maria S. | M74: {=_xlfn.IFS(OR('Original Data'!M74=0,'Original Data'!M74="No",'Original Data'!M74=FALSE),"No",OR('Original Data'!M74=1,'Original Data'!M74="Yes",'Original Data'!M74=TRUE),"Yes")} -> Yes
A75: 74 | B75: P020 | C75: 44958 | D75: Crossbody Bag | E75: Banana Republic | F75: S004 | G75: South | H75: 1 | I75: 0.1 | J75: 53.96 | K75: =PROPER('Original Data'!K75) -> Apple Pay | L75: Tom B. | M75: {=_xlfn.IFS(OR('Original Data'!M75=0,'Original Data'!M75="No",'Original Data'!M75=FALSE),"No",OR('Original Data'!M75=1,'Original Data'!M75="Yes",'Original Data'!M75=TRUE),"Yes")} -> Yes
A76: 75 | B76: P003 | C76: 45538 | D76: Puffer Jacket | E76: GAP | F76: S003 | G76: Midwest | H76: 2 | I76: 0.1 | J76: 232.2 | K76: =PROPER('Original Data'!K76) -> Gift Card | L76: David N. | M76: {=_xlfn.IFS(OR('Original Data'!M76=0,'Original Data'!M76="No",'Original Data'!M76=FALSE),"No",OR('Original Data'!M76=1,'Original Data'!M76="Yes",'Original Data'!M76=TRUE),"Yes")} -> Yes
A77: 76 | B77: P014 | C77: 45391 | D77: Wrap Dress | E77: Intermix | F77: S004 | G77: South | H77: 4 | I77: 0.05 | J77: 341.81 | K77: =PROPER('Original Data'!K77) -> Cash | L77: Priya M. | M77: {=_xlfn.IFS(OR('Original Data'!M77=0,'Original Data'!M77="No",'Original Data'!M77=FALSE),"No",OR('Original Data'!M77=1,'Original Data'!M77="Yes",'Original Data'!M77=TRUE),"Yes")} -> Yes
A78: 77 | B78: P003 | C78: 45308 | D78: Puffer Jacket | E78: GAP | F78: S002 | G78: West | H78: 1 | I78: 0 | J78: 129 | K78: =PROPER('Original Data'!K78) -> Credit Card | L78: Priya M. | M78: {=_xlfn.IFS(OR('Original Data'!M78=0,'Original Data'!M78="No",'Original Data'!M78=FALSE),"No",OR('Original Data'!M78=1,'Original Data'!M78="Yes",'Original Data'!M78=TRUE),"Yes")} -> Yes
A79: 78 | B79: P010 | C79: 45518 | D79: High-Rise Jeans | E79: GAP | F79: S001 | G79: Northeast | H79: 5 | I79: 0.1 | J79: 314.78 | K79: =PROPER('Original Data'!K79) -> Credit Card | L79: David N. | M79: {=_xlfn.IFS(OR('Original Data'!M79=0,'Original Data'!M79="No",'Original Data'!M79=FALSE),"No",OR('Original Data'!M79=1,'Original Data'!M79="Yes",'Original Data'!M79=TRUE),"Yes")} -> No
A80: 79 | B80: P018 | C80: 45111 | D80: Rain Jacket | E80: Old Navy | F80: S007 | G80: Northeast | H80: 5 | J80: 425 | K80: =PROPER('Original Data'!K80) -> Credit Card | L80: Amy K. | M80: {=_xlfn.IFS(OR('Original Data'!M80=0,'Original Data'!M80="No",'Original Data'!M80=FALSE),"No",OR('Original Data'!M80=1,'Original Data'!M80="Yes",'Original Data'!M80=TRUE),"Yes")} -> Yes
A81: 80 | B81: P003 | C81: 45391 | D81: Puffer Jacket | E81: GAP | F81: S001 | G81: Northeast | H81: 5 | I81: 0.05 | J81: 612.75 | K81: =PROPER('Original Data'!K81) -> Gift Card | L81: Priya M. | M81: {=_xlfn.IFS(OR('Original Data'!M81=0,'Original Data'!M81="No",'Original Data'!M81=FALSE),"No",OR('Original Data'!M81=1,'Original Data'!M81="Yes",'Original Data'!M81=TRUE),"Yes")} -> Yes
A82: 81 | B82: P003 | C82: 45548 | D82: Puffer Jacket | E82: GAP | F82: S001 | G82: Northeast | H82: 3 | I82: 0.25 | J82: 290.25 | K82: =PROPER('Original Data'!K82) -> Gift Card | L82: Priya M. | M82: {=_xlfn.IFS(OR('Original Data'!M82=0,'Original Data'!M82="No",'Original Data'!M82=FALSE),"No",OR('Original Data'!M82=1,'Original Data'!M82="Yes",'Original Data'!M82=TRUE),"Yes")} -> Yes
A83: 82 | B83: P002 | C83: 45136 | D83: Slim Chino Pants | E83: GAP | F83: S005 | G83: Southeast | H83: 2 | I83: 0.2 | J83: 95.92 | K83: =PROPER('Original Data'!K83) -> Credit Card | L83: Maria S. | M83: {=_xlfn.IFS(OR('Original Data'!M83=0,'Original Data'!M83="No",'Original Data'!M83=FALSE),"No",OR('Original Data'!M83=1,'Original Data'!M83="Yes",'Original Data'!M83=TRUE),"Yes")} -> Yes
A84: 83 | B84: P017 | C84: 44970 | D84: Cargo Shorts | E84: Old Navy | G84: NULL | H84: 5 | I84: 0.15 | J84: 169.79 | K84: =PROPER('Original Data'!K84) -> Gift Card | L84: James T. | M84: {=_xlfn.IFS(OR('Original Data'!M84=0,'Original Data'!M84="No",'Original Data'!M84=FALSE),"No",OR('Original Data'!M84=1,'Original Data'!M84="Yes",'Original Data'!M84=TRUE),"Yes")} -> Yes
A85: 84 | B85: P011 | C85: 45374 | D85: Trench Coat | E85: Banana Republic | F85: S001 | G85: Northeast | H85: 2 | I85: 0.25 | J85: 297 | K85: =PROPER('Original Data'!K85) -> Credit Card | L85: David N. | M85: {=_xlfn.IFS(OR('Original Data'!M85=0,'Original Data'!M85="No",'Original Data'!M85=FALSE),"No",OR('Original Data'!M85=1,'Original Data'!M85="Yes",'Original Data'!M85=TRUE),"Yes")} -> No
A86: 85 | B86: P017 | C86: 45587 | D86: Cargo Shorts | E86: Old Navy | F86: S002 | G86: West | H86: 5 | I86: 0.05 | J86: 189.76 | K86: =PROPER('Original Data'!K86) -> Cash | L86: David N. | M86: {=_xlfn.IFS(OR('Original Data'!M86=0,'Original Data'!M86="No",'Original Data'!M86=FALSE),"No",OR('Original Data'!M86=1,'Original Data'!M86="Yes",'Original Data'!M86=TRUE),"Yes")} -> Yes
A87: 86 | B87: P015 | C87: 45250 | D87: Sports Bra | E87: Athleta | F87: S008 | H87: 5 | I87: 0.25 | J87: 168.56 | K87: =PROPER('Original Data'!K87) -> Apple Pay | L87: David N. | M87: {=_xlfn.IFS(OR('Original Data'!M87=0,'Original Data'!M87="No",'Original Data'!M87=FALSE),"No",OR('Original Data'!M87=1,'Original Data'!M87="Yes",'Original Data'!M87=TRUE),"Yes")} -> Yes
A88: 87 | B88: P002 | C88: 45019 | D88: =VLOOKUP(B88,'Original Data'!B:D,3,FALSE) -> Slim Chino Pants | E88: =_xlfn.XLOOKUP('Cleaned Data'!B53,'Original Data'!B:B,'Original Data'!E:E) -> GAP | F88: S001 | G88: Northeast | H88: 3 | I88: 0.1 | J88: 161.87 | K88: =PROPER('Original Data'!K88) -> Apple Pay | L88: James T. | M88: Unknown
A89: 88 | B89: P011 | C89: 45388 | D89: =VLOOKUP(B89,'Original Data'!B:D,3,FALSE) -> Trench Coat | E89: =_xlfn.XLOOKUP('Cleaned Data'!B591,'Original Data'!B:B,'Original Data'!E:E) -> GAP | F89: S004 | G89: South | H89: 5 | I89: 0.25 | J89: 742.5 | K89: =PROPER('Original Data'!K89) -> Credit Card | L89: Lin W. | M89: Unknown
A90: 89 | B90: P012 | C90: 45273 | D90: Ankle Boots | E90: Banana Republic | F90: S003 | G90: Midwest | H90: 3 | I90: 0.1 | J90: 321.3 | K90: =PROPER('Original Data'!K90) -> Gift Card | L90: Priya M. | M90: {=_xlfn.IFS(OR('Original Data'!M90=0,'Original Data'!M90="No",'Original Data'!M90=FALSE),"No",OR('Original Data'!M90=1,'Original Data'!M90="Yes",'Original Data'!M90=TRUE),"Yes")} -> No
A91: 90 | B91: P011 | C91: 45598 | D91: Trench Coat | E91: Banana Republic | F91: S003 | G91: Midwest | H91: 1 | I91: 0 | J91: 198 | K91: =PROPER('Original Data'!K91) -> Cash | L91: David N. | M91: {=_xlfn.IFS(OR('Original Data'!M91=0,'Original Data'!M91="No",'Original Data'!M91=FALSE),"No",OR('Original Data'!M91=1,'Original Data'!M91="Yes",'Original Data'!M91=TRUE),"Yes")} -> No
A92: 91 | B92: P017 | C92: 45298 | D92: Cargo Shorts | E92: Old Navy | F92: S003 | G92: Midwest | H92: 1 | I92: 0.2 | J92: 31.96 | K92: =PROPER('Original Data'!K92) -> Credit Card | L92: David N. | M92: {=_xlfn.IFS(OR('Original Data'!M92=0,'Original Data'!M92="No",'Original Data'!M92=FALSE),"No",OR('Original Data'!M92=1,'Original Data'!M92="Yes",'Original Data'!M92=TRUE),"Yes")} -> Yes
A93: 92 | B93: P017 | C93: 45061 | D93: Cargo Shorts | E93: Old Navy | F93: S002 | G93: West | H93: 5 | I93: 0 | J93: 199.75 | K93: PayPal | L93: David N. | M93: {=_xlfn.IFS(OR('Original Data'!M93=0,'Original Data'!M93="No",'Original Data'!M93=FALSE),"No",OR('Original Data'!M93=1,'Original Data'!M93="Yes",'Original Data'!M93=TRUE),"Yes")} -> Yes
A94: 93 | B94: P015 | C94: 45473 | D94: Sports Bra | E94: Athleta | F94: S004 | G94: South | H94: 5 | I94: 0.1 | J94: 202.28 | K94: =PROPER('Original Data'!K94) -> Debit Card | L94: Tom B. | M94: {=_xlfn.IFS(OR('Original Data'!M94=0,'Original Data'!M94="No",'Original Data'!M94=FALSE),"No",OR('Original Data'!M94=1,'Original Data'!M94="Yes",'Original Data'!M94=TRUE),"Yes")} -> Yes
A95: 94 | B95: P013 | C95: 45546 | D95: Silk Scarf | E95: Intermix | F95: S005 | G95: Southeast | H95: 5 | I95: 0.2 | J95: 179.8 | K95: =PROPER('Original Data'!K95) -> Debit Card | L95: Lin W. | M95: {=_xlfn.IFS(OR('Original Data'!M95=0,'Original Data'!M95="No",'Original Data'!M95=FALSE),"No",OR('Original Data'!M95=1,'Original Data'!M95="Yes",'Original Data'!M95=TRUE),"Yes")} -> No
A96: 95 | B96: P010 | C96: 45452 | D96: High-Rise Jeans | E96: GAP | F96: S002 | G96: West | H96: 1 | I96: 0 | J96: 69.95 | K96: =PROPER('Original Data'!K96) -> Gift Card | L96: Amy K. | M96: {=_xlfn.IFS(OR('Original Data'!M96=0,'Original Data'!M96="No",'Original Data'!M96=FALSE),"No",OR('Original Data'!M96=1,'Original Data'!M96="Yes",'Original Data'!M96=TRUE),"Yes")} -> No
A97: 96 | B97: P017 | C97: 45310 | D97: Cargo Shorts | E97: Old Navy | G97: NULL | H97: 3 | I97: 0.05 | J97: 113.86 | K97: =PROPER('Original Data'!K97) -> Credit Card | L97: Priya M. | M97: {=_xlfn.IFS(OR('Original Data'!M97=0,'Original Data'!M97="No",'Original Data'!M97=FALSE),"No",OR('Original Data'!M97=1,'Original Data'!M97="Yes",'Original Data'!M97=TRUE),"Yes")} -> Yes
A98: 97 | B98: P016 | C98: 45189 | D98: Graphic Hoodie | E98: Old Navy | F98: S003 | G98: Midwest | H98: 4 | I98: 0 | J98: 199.8 | K98: =PROPER('Original Data'!K98) -> Credit Card | L98: James T. | M98: {=_xlfn.IFS(OR('Original Data'!M98=0,'Original Data'!M98="No",'Original Data'!M98=FALSE),"No",OR('Original Data'!M98=1,'Original Data'!M98="Yes",'Original Data'!M98=TRUE),"Yes")} -> No
A99: 98 | B99: P020 | C99: 45538 | D99: Crossbody Bag | E99: Banana Republic | G99: NULL | H99: 4 | I99: 0 | J99: 239.8 | K99: =PROPER('Original Data'!K99) -> Gift Card | L99: James T. | M99: {=_xlfn.IFS(OR('Original Data'!M99=0,'Original Data'!M99="No",'Original Data'!M99=FALSE),"No",OR('Original Data'!M99=1,'Original Data'!M99="Yes",'Original Data'!M99=TRUE),"Yes")} -> Yes
A100: 99 | B100: P017 | C100: 45408 | D100: Cargo Shorts | E100: Old Navy | F100: S002 | G100: West | H100: 3 | I100: 0 | J100: 119.85 | K100: =PROPER('Original Data'!K100) -> Gift Card | L100: Maria S. | M100: {=_xlfn.IFS(OR('Original Data'!M100=0,'Original Data'!M100="No",'Original Data'!M100=FALSE),"No",OR('Original Data'!M100=1,'Original Data'!M100="Yes",'Original Data'!M100=TRUE),"Yes")} -> Yes
...
